{
  "id": "1d8b1e42-1e56-42bb-ae4d-96ab52c42d99",
  "name": "Stress Detector API - Local",
  "values": [
    {
      "key": "base_url",
      "value": "http://localhost:3000",
      "type": "default",
      "enabled": true
    },
    {
      "key": "test_email",
      "value": "student@example.com",
      "type": "default",
      "enabled": true
    },
    {
      "key": "test_password",
      "value": "password123",
      "type": "secret",
      "enabled": true
    },
    {
      "key": "accessToken",
      "value": "",
      "type": "secret",
      "enabled": true
    },
    {
      "key": "refreshToken",
      "value": "",
      "type": "secret",
      "enabled": true
    },
    {
      "key": "user_id",
      "value": "",
      "type": "default",
      "enabled": true
    },
    {
      "key": "activity_id",
      "value": "",
      "type": "default",
      "enabled": true
    },
    {
      "key": "recommendation_id",
      "value": "",
      "type": "default",
      "enabled": true
    }
  ],
  "_postman_variable_scope": "environment"
}
